README.md
setup.py
web_dict/__init__.py
web_dict.egg-info/PKG-INFO
web_dict.egg-info/SOURCES.txt
web_dict.egg-info/dependency_links.txt
web_dict.egg-info/requires.txt
web_dict.egg-info/top_level.txt
web_dict/core/__init__.py
web_dict/core/exception.py
web_dict/core/factory.py
web_dict/core/parser.py
web_dict/core/utils.py
web_dict/core/prviders/__init__.py
web_dict/core/prviders/base_provider.py
web_dict/core/prviders/cn_bing.py
web_dict/core/prviders/cn_bing_s.py
web_dict/core/prviders/collinsdictionary.py
web_dict/core/prviders/lexico.py
web_dict/core/prviders/spanishdict.py
web_dict/core/prviders/urbandictionary.py
web_dict/core/prviders/vocabulary_s.py
web_dict/core/prviders/vocaublary.py
web_dict/core/prviders/youdao_ec.py
web_dict/tests/__init__.py
web_dict/tests/test_bing.py
web_dict/tests/test_collins.py
web_dict/tests/test_dict_factory.py
web_dict/tests/test_lexico.py
web_dict/tests/test_spanidict.py
web_dict/tests/test_ub.py
web_dict/tests/test_vocabulary.py
web_dict/tests/test_youdao.py