Metadata-Version: 2.1
Name: web-dict
Version: 0.1.91
Summary: parser class for vaiouse online-dict, e.g. collinsdictionary/lexico/vocabulary/spanishdict etc.
Home-page: https://github.com/upday7/web_dict
Author: Kyle, Hwang
Author-email: upday7@163.com
License: agpl-3.0
Keywords: dictionary,spanish,english,chinese,collins,oxford,lexico
Platform: UNKNOWN
Classifier: Development Status :: 5 - Production/Stable
Classifier: Intended Audience :: Developers
Classifier: Programming Language :: Python :: 3.8
